MANIFEST.in
README.txt
setup.py
docs/HISTORY.txt
docs/LICENSE.txt
src/silva/__init__.py
src/silva.system.utils.egg-info/PKG-INFO
src/silva.system.utils.egg-info/SOURCES.txt
src/silva.system.utils.egg-info/dependency_links.txt
src/silva.system.utils.egg-info/entry_points.txt
src/silva.system.utils.egg-info/namespace_packages.txt
src/silva.system.utils.egg-info/not-zip-safe
src/silva.system.utils.egg-info/requires.txt
src/silva.system.utils.egg-info/top_level.txt
src/silva/system/__init__.py
src/silva/system/utils/__init__.py
src/silva/system/utils/script.py
src/silva/system/utils/commands/__init__.py
src/silva/system/utils/commands/files.py
src/silva/system/utils/commands/manage.py
src/silva/system/utils/commands/pack.py
src/silva/system/utils/commands/version.py
src/silva/system/utils/commands/xml.py
src/silva/system/utils/commands/zexp.py