Metadata-Version: 1.1
Name: silva.system.utils
Version: 1.4.2
Summary: Command line utils to manage Silva sites
Home-page: https://github.com/silvacms/silva.system.utils
Author: Infrae
Author-email: info@infrae.com
License: BSD
Keywords: system utils silva
Platform: UNKNOWN
Classifier: Environment :: Web Environment
Classifier: Intended Audience :: Developers
Classifier: License :: OSI Approved :: Zope Public License
Classifier: Programming Language :: Python
Classifier: Topic :: Software Development :: Libraries :: Python Modules
Classifier: Framework :: Zope2
